terraform_usage/__init__.py
terraform_usage/__main__.py
terraform_usage-2.2.2.data/scripts/tfc_usage
terraform_usage-2.2.2.dist-info/METADATA
terraform_usage-2.2.2.dist-info/WHEEL
terraform_usage-2.2.2.dist-info/entry_points.txt
terraform_usage-2.2.2.dist-info/RECORD
