Metadata-Version: 2.1
Name: terraform_usage
Version: 2.2.2
Summary: Get Terraform usage statistics.
Home-page: https://gitlab.com/fer1035_python/modules/pypi-terraform_usage
License: GPL-2.0-only
Keywords: Terraform,Cloud,usage,statistics
Author: Ahmad Ferdaus Abd Razak
Author-email: fer1035@gmail.com
Requires-Python: >=3.9,<4.0
Classifier: License :: OSI Approved :: GNU General Public License v2 (GPLv2)
Classifier: Programming Language :: Python :: 3
Classifier: Programming Language :: Python :: 3.9
Classifier: Programming Language :: Python :: 3.10
Classifier: Programming Language :: Python :: 3.11
Classifier: Programming Language :: Python :: 3.12
Requires-Dist: requests (>=2.27.1,<3.0.0)
Project-URL: Repository, https://gitlab.com/fer1035_python/modules/pypi-terraform_usage
